{"@t":"2023-09-25T09:12:52.6734202Z","@mt":"Database Migrated","Application":"webApi"}
{"@t":"2023-09-25T09:12:54.2770104Z","@mt":"Now listening on: {address}","address":"https://localhost:7167","EventId":{"Id":14,"Name":"ListeningOnAddress"},"SourceContext":"Microsoft.Hosting.Lifetime","Application":"webApi"}
{"@t":"2023-09-25T09:12:54.2880471Z","@mt":"Now listening on: {address}","address":"http://localhost:5263","EventId":{"Id":14,"Name":"ListeningOnAddress"},"SourceContext":"Microsoft.Hosting.Lifetime","Application":"webApi"}
{"@t":"2023-09-25T09:12:54.2976034Z","@mt":"Application started. Press Ctrl+C to shut down.","SourceContext":"Microsoft.Hosting.Lifetime","Application":"webApi"}
{"@t":"2023-09-25T09:12:54.3018213Z","@mt":"Hosting environment: {envName}","envName":"Development","SourceContext":"Microsoft.Hosting.Lifetime","Application":"webApi"}
{"@t":"2023-09-25T09:12:54.3044216Z","@mt":"Content root path: {contentRoot}","contentRoot":"C:\\Users\\milan\\exameplanner_smort\\exame-tool-api\\Smort-Examen-Tool-API\\VistaExamenPlanner","SourceContext":"Microsoft.Hosting.Lifetime","Application":"webApi"}
{"@t":"2023-09-25T09:12:56.6829622Z","@mt":"HTTP {RequestMethod} {RequestPath} responded {StatusCode} in {Elapsed:0.0000} ms","@r":["69.5050"],"RequestMethod":"GET","RequestPath":"/swagger","StatusCode":301,"Elapsed":69.505,"SourceContext":"Serilog.AspNetCore.RequestLoggingMiddleware","Application":"webApi"}
{"@t":"2023-09-25T09:12:57.2216572Z","@mt":"HTTP {RequestMethod} {RequestPath} responded {StatusCode} in {Elapsed:0.0000} ms","@r":["489.8922"],"RequestMethod":"GET","RequestPath":"/swagger/index.html","StatusCode":200,"Elapsed":489.8922,"SourceContext":"Serilog.AspNetCore.RequestLoggingMiddleware","Application":"webApi"}
{"@t":"2023-09-25T09:12:57.4265290Z","@mt":"HTTP {RequestMethod} {RequestPath} responded {StatusCode} in {Elapsed:0.0000} ms","@r":["176.9192"],"RequestMethod":"GET","RequestPath":"/swagger/swagger-ui-standalone-preset.js","StatusCode":200,"Elapsed":176.9192,"SourceContext":"Serilog.AspNetCore.RequestLoggingMiddleware","Application":"webApi"}
{"@t":"2023-09-25T09:12:57.4265440Z","@mt":"HTTP {RequestMethod} {RequestPath} responded {StatusCode} in {Elapsed:0.0000} ms","@r":["174.6404"],"RequestMethod":"GET","RequestPath":"/swagger/swagger-ui.css","StatusCode":200,"Elapsed":174.6404,"SourceContext":"Serilog.AspNetCore.RequestLoggingMiddleware","Application":"webApi"}
{"@t":"2023-09-25T09:12:57.4767019Z","@mt":"HTTP {RequestMethod} {RequestPath} responded {StatusCode} in {Elapsed:0.0000} ms","@r":["227.1173"],"RequestMethod":"GET","RequestPath":"/swagger/swagger-ui-bundle.js","StatusCode":200,"Elapsed":227.1173,"SourceContext":"Serilog.AspNetCore.RequestLoggingMiddleware","Application":"webApi"}
{"@t":"2023-09-25T09:12:58.2093336Z","@mt":"HTTP {RequestMethod} {RequestPath} responded {StatusCode} in {Elapsed:0.0000} ms","@r":["152.9693"],"RequestMethod":"GET","RequestPath":"/swagger/v1/swagger.json","StatusCode":200,"Elapsed":152.9693,"SourceContext":"Serilog.AspNetCore.RequestLoggingMiddleware","Application":"webApi"}
{"@t":"2023-09-25T09:17:20.3316469Z","@mt":"HTTP {RequestMethod} {RequestPath} responded {StatusCode} in {Elapsed:0.0000} ms","@r":["147.5664"],"RequestMethod":"POST","RequestPath":"/MakeExamen","StatusCode":400,"Elapsed":147.5664,"SourceContext":"Serilog.AspNetCore.RequestLoggingMiddleware","Application":"webApi"}
{"@t":"2023-09-25T09:18:05.0701971Z","@mt":"HTTP {RequestMethod} {RequestPath} responded {StatusCode} in {Elapsed:0.0000} ms","@r":["27.5919"],"RequestMethod":"POST","RequestPath":"/MakeExamen","StatusCode":400,"Elapsed":27.5919,"SourceContext":"Serilog.AspNetCore.RequestLoggingMiddleware","Application":"webApi"}
{"@t":"2023-09-25T09:18:05.7731630Z","@mt":"HTTP {RequestMethod} {RequestPath} responded {StatusCode} in {Elapsed:0.0000} ms","@r":["1.7011"],"RequestMethod":"POST","RequestPath":"/MakeExamen","StatusCode":400,"Elapsed":1.7011,"SourceContext":"Serilog.AspNetCore.RequestLoggingMiddleware","Application":"webApi"}
{"@t":"2023-09-25T09:19:20.6138543Z","@mt":"HTTP {RequestMethod} {RequestPath} responded {StatusCode} in {Elapsed:0.0000} ms","@r":["28.4307"],"RequestMethod":"POST","RequestPath":"/MakeExamen","StatusCode":400,"Elapsed":28.4307,"SourceContext":"Serilog.AspNetCore.RequestLoggingMiddleware","Application":"webApi"}
{"@t":"2023-09-25T09:30:43.6388770Z","@mt":"HTTP {RequestMethod} {RequestPath} responded {StatusCode} in {Elapsed:0.0000} ms","@r":["72.6774"],"RequestMethod":"POST","RequestPath":"/MakeExamen","StatusCode":400,"Elapsed":72.6774,"SourceContext":"Serilog.AspNetCore.RequestLoggingMiddleware","Application":"webApi"}
{"@t":"2023-09-25T09:33:16.4011925Z","@mt":"HTTP {RequestMethod} {RequestPath} responded {StatusCode} in {Elapsed:0.0000} ms","@r":["19.2283"],"RequestMethod":"POST","RequestPath":"/MakeExamen","StatusCode":400,"Elapsed":19.2283,"SourceContext":"Serilog.AspNetCore.RequestLoggingMiddleware","Application":"webApi"}
{"@t":"2023-09-25T09:48:24.4517113Z","@mt":"Database Migrated","Application":"webApi"}
{"@t":"2023-09-25T09:48:25.6210800Z","@mt":"Now listening on: {address}","address":"https://localhost:7167","EventId":{"Id":14,"Name":"ListeningOnAddress"},"SourceContext":"Microsoft.Hosting.Lifetime","Application":"webApi"}
{"@t":"2023-09-25T09:48:25.6267966Z","@mt":"Now listening on: {address}","address":"http://localhost:5263","EventId":{"Id":14,"Name":"ListeningOnAddress"},"SourceContext":"Microsoft.Hosting.Lifetime","Application":"webApi"}
{"@t":"2023-09-25T09:48:25.6334441Z","@mt":"Application started. Press Ctrl+C to shut down.","SourceContext":"Microsoft.Hosting.Lifetime","Application":"webApi"}
{"@t":"2023-09-25T09:48:25.6370690Z","@mt":"Hosting environment: {envName}","envName":"Development","SourceContext":"Microsoft.Hosting.Lifetime","Application":"webApi"}
{"@t":"2023-09-25T09:48:25.6395037Z","@mt":"Content root path: {contentRoot}","contentRoot":"C:\\Users\\milan\\exameplanner_smort\\exame-tool-api\\Smort-Examen-Tool-API\\VistaExamenPlanner","SourceContext":"Microsoft.Hosting.Lifetime","Application":"webApi"}
{"@t":"2023-09-25T09:48:27.9309602Z","@mt":"HTTP {RequestMethod} {RequestPath} responded {StatusCode} in {Elapsed:0.0000} ms","@r":["560.2225"],"RequestMethod":"GET","RequestPath":"/swagger/index.html","StatusCode":200,"Elapsed":560.2225,"SourceContext":"Serilog.AspNetCore.RequestLoggingMiddleware","Application":"webApi"}
{"@t":"2023-09-25T09:48:28.5742712Z","@mt":"HTTP {RequestMethod} {RequestPath} responded {StatusCode} in {Elapsed:0.0000} ms","@r":["141.3517"],"RequestMethod":"GET","RequestPath":"/swagger/v1/swagger.json","StatusCode":200,"Elapsed":141.3517,"SourceContext":"Serilog.AspNetCore.RequestLoggingMiddleware","Application":"webApi"}
{"@t":"2023-09-25T09:50:14.8579793Z","@mt":"HTTP {RequestMethod} {RequestPath} responded {StatusCode} in {Elapsed:0.0000} ms","@r":["442.6598"],"RequestMethod":"GET","RequestPath":"/GetExamensList","StatusCode":200,"Elapsed":442.6598,"SourceContext":"Serilog.AspNetCore.RequestLoggingMiddleware","Application":"webApi"}
{"@t":"2023-09-25T10:00:58.2865264Z","@mt":"HTTP {RequestMethod} {RequestPath} responded {StatusCode} in {Elapsed:0.0000} ms","@r":["125.9002"],"RequestMethod":"GET","RequestPath":"/GetExamensList","StatusCode":200,"Elapsed":125.9002,"SourceContext":"Serilog.AspNetCore.RequestLoggingMiddleware","Application":"webApi"}
{"@t":"2023-09-25T10:00:59.2001655Z","@mt":"HTTP {RequestMethod} {RequestPath} responded {StatusCode} in {Elapsed:0.0000} ms","@r":["9.0525"],"RequestMethod":"GET","RequestPath":"/GetExamensList","StatusCode":200,"Elapsed":9.0525,"SourceContext":"Serilog.AspNetCore.RequestLoggingMiddleware","Application":"webApi"}
{"@t":"2023-09-25T10:23:22.2693556Z","@mt":"HTTP {RequestMethod} {RequestPath} responded {StatusCode} in {Elapsed:0.0000} ms","@r":["78.1949"],"RequestMethod":"GET","RequestPath":"/GetExamensList","StatusCode":200,"Elapsed":78.1949,"SourceContext":"Serilog.AspNetCore.RequestLoggingMiddleware","Application":"webApi"}
{"@t":"2023-09-25T12:12:54.8566644Z","@mt":"Database Migrated","Application":"webApi"}
{"@t":"2023-09-25T12:12:55.7805727Z","@mt":"Now listening on: {address}","address":"https://localhost:7167","EventId":{"Id":14,"Name":"ListeningOnAddress"},"SourceContext":"Microsoft.Hosting.Lifetime","Application":"webApi"}
{"@t":"2023-09-25T12:12:55.7880917Z","@mt":"Now listening on: {address}","address":"http://localhost:5263","EventId":{"Id":14,"Name":"ListeningOnAddress"},"SourceContext":"Microsoft.Hosting.Lifetime","Application":"webApi"}
{"@t":"2023-09-25T12:12:55.7942530Z","@mt":"Application started. Press Ctrl+C to shut down.","SourceContext":"Microsoft.Hosting.Lifetime","Application":"webApi"}
{"@t":"2023-09-25T12:12:55.7963010Z","@mt":"Hosting environment: {envName}","envName":"Development","SourceContext":"Microsoft.Hosting.Lifetime","Application":"webApi"}
{"@t":"2023-09-25T12:12:55.7984509Z","@mt":"Content root path: {contentRoot}","contentRoot":"C:\\Users\\milan\\exameplanner_smort\\exame-tool-api\\Smort-Examen-Tool-API\\VistaExamenPlanner","SourceContext":"Microsoft.Hosting.Lifetime","Application":"webApi"}
{"@t":"2023-09-25T12:12:59.2668792Z","@mt":"HTTP {RequestMethod} {RequestPath} responded {StatusCode} in {Elapsed:0.0000} ms","@r":["233.8787"],"RequestMethod":"GET","RequestPath":"/swagger","StatusCode":301,"Elapsed":233.8787,"SourceContext":"Serilog.AspNetCore.RequestLoggingMiddleware","Application":"webApi"}
{"@t":"2023-09-25T12:13:00.2751157Z","@mt":"HTTP {RequestMethod} {RequestPath} responded {StatusCode} in {Elapsed:0.0000} ms","@r":["760.2132"],"RequestMethod":"GET","RequestPath":"/swagger/index.html","StatusCode":200,"Elapsed":760.2132,"SourceContext":"Serilog.AspNetCore.RequestLoggingMiddleware","Application":"webApi"}
{"@t":"2023-09-25T12:13:00.4889402Z","@mt":"HTTP {RequestMethod} {RequestPath} responded {StatusCode} in {Elapsed:0.0000} ms","@r":["215.2337"],"RequestMethod":"GET","RequestPath":"/swagger/swagger-ui-standalone-preset.js","StatusCode":200,"Elapsed":215.2337,"SourceContext":"Serilog.AspNetCore.RequestLoggingMiddleware","Application":"webApi"}
{"@t":"2023-09-25T12:13:00.4889435Z","@mt":"HTTP {RequestMethod} {RequestPath} responded {StatusCode} in {Elapsed:0.0000} ms","@r":["215.2501"],"RequestMethod":"GET","RequestPath":"/swagger/swagger-ui.css","StatusCode":200,"Elapsed":215.2501,"SourceContext":"Serilog.AspNetCore.RequestLoggingMiddleware","Application":"webApi"}
{"@t":"2023-09-25T12:13:00.5374989Z","@mt":"HTTP {RequestMethod} {RequestPath} responded {StatusCode} in {Elapsed:0.0000} ms","@r":["263.7854"],"RequestMethod":"GET","RequestPath":"/swagger/swagger-ui-bundle.js","StatusCode":200,"Elapsed":263.7854,"SourceContext":"Serilog.AspNetCore.RequestLoggingMiddleware","Application":"webApi"}
{"@t":"2023-09-25T12:13:01.6999345Z","@mt":"HTTP {RequestMethod} {RequestPath} responded {StatusCode} in {Elapsed:0.0000} ms","@r":["339.9994"],"RequestMethod":"GET","RequestPath":"/swagger/v1/swagger.json","StatusCode":200,"Elapsed":339.9994,"SourceContext":"Serilog.AspNetCore.RequestLoggingMiddleware","Application":"webApi"}
{"@t":"2023-09-25T12:14:04.0481571Z","@mt":"HTTP {RequestMethod} {RequestPath} responded {StatusCode} in {Elapsed:0.0000} ms","@r":["32283.3564"],"@l":"Error","@x":"System.ArgumentNullException: Value cannot be null. (Parameter 'logger')\r\n   at System.ThrowHelper.Throw(String paramName)\r\n   at Microsoft.Extensions.Logging.LoggerExtensions.Log(ILogger logger, LogLevel logLevel, EventId eventId, Exception exception, String message, Object[] args)\r\n   at Microsoft.Extensions.Logging.LoggerExtensions.Log(ILogger logger, LogLevel logLevel, String message, Object[] args)\r\n   at VistaExamenPlanner.Handler.DatabaseHandler.Select(MySqlCommand sqlCommand) in C:\\Users\\milan\\exameplanner_smort\\exame-tool-api\\Smort-Examen-Tool-API\\VistaExamenPlanner.Handler\\DatabaseHandler.cs:line 70\r\n   at VistaExamenPlanner.Controllers.ExamenPlanner.GetExamensStudent() in C:\\Users\\milan\\exameplanner_smort\\exame-tool-api\\Smort-Examen-Tool-API\\VistaExamenPlanner\\Controllers\\ExamenPlanner.cs:line 40\r\n   at lambda_method2(Closure , Object , Object[] )\r\n   at Microsoft.AspNetCore.Mvc.Infrastructure.ActionMethodExecutor.SyncObjectResultExecutor.Execute(IActionResultTypeMapper mapper, ObjectMethodExecutor executor, Object controller, Object[] arguments)\r\n   at Microsoft.AspNetCore.Mvc.Infrastructure.ControllerActionInvoker.InvokeActionMethodAsync()\r\n   at Microsoft.AspNetCore.Mvc.Infrastructure.ControllerActionInvoker.Next(State& next, Scope& scope, Object& state, Boolean& isCompleted)\r\n   at Microsoft.AspNetCore.Mvc.Infrastructure.ControllerActionInvoker.InvokeNextActionFilterAsync()\r\n--- End of stack trace from previous location ---\r\n   at Microsoft.AspNetCore.Mvc.Infrastructure.ControllerActionInvoker.Rethrow(ActionExecutedContextSealed context)\r\n   at Microsoft.AspNetCore.Mvc.Infrastructure.ControllerActionInvoker.Next(State& next, Scope& scope, Object& state, Boolean& isCompleted)\r\n   at Microsoft.AspNetCore.Mvc.Infrastructure.ControllerActionInvoker.InvokeInnerFilterAsync()\r\n--- End of stack trace from previous location ---\r\n   at Microsoft.AspNetCore.Mvc.Infrastructure.ResourceInvoker.<InvokeNextResourceFilter>g__Awaited|25_0(ResourceInvoker invoker, Task lastTask, State next, Scope scope, Object state, Boolean isCompleted)\r\n   at Microsoft.AspNetCore.Mvc.Infrastructure.ResourceInvoker.Rethrow(ResourceExecutedContextSealed context)\r\n   at Microsoft.AspNetCore.Mvc.Infrastructure.ResourceInvoker.Next(State& next, Scope& scope, Object& state, Boolean& isCompleted)\r\n   at Microsoft.AspNetCore.Mvc.Infrastructure.ResourceInvoker.InvokeFilterPipelineAsync()\r\n--- End of stack trace from previous location ---\r\n   at Microsoft.AspNetCore.Mvc.Infrastructure.ResourceInvoker.<InvokeAsync>g__Awaited|17_0(ResourceInvoker invoker, Task task, IDisposable scope)\r\n   at Microsoft.AspNetCore.Mvc.Infrastructure.ResourceInvoker.<InvokeAsync>g__Awaited|17_0(ResourceInvoker invoker, Task task, IDisposable scope)\r\n   at Microsoft.AspNetCore.Routing.EndpointMiddleware.<Invoke>g__AwaitRequestTask|6_0(Endpoint endpoint, Task requestTask, ILogger logger)\r\n   at Swashbuckle.AspNetCore.SwaggerUI.SwaggerUIMiddleware.Invoke(HttpContext httpContext)\r\n   at Swashbuckle.AspNetCore.Swagger.SwaggerMiddleware.Invoke(HttpContext httpContext, ISwaggerProvider swaggerProvider)\r\n   at Microsoft.AspNetCore.Authentication.AuthenticationMiddleware.Invoke(HttpContext context)\r\n   at Serilog.AspNetCore.RequestLoggingMiddleware.Invoke(HttpContext httpContext)","RequestMethod":"GET","RequestPath":"/GetExamenListOfClass","StatusCode":500,"Elapsed":32283.3564,"SourceContext":"Serilog.AspNetCore.RequestLoggingMiddleware","Application":"webApi"}
{"@t":"2023-09-25T12:14:04.1023169Z","@mt":"Connection id \"{ConnectionId}\", Request id \"{TraceIdentifier}\": An unhandled exception was thrown by the application.","@l":"Error","@x":"System.ArgumentNullException: Value cannot be null. (Parameter 'logger')\r\n   at System.ThrowHelper.Throw(String paramName)\r\n   at Microsoft.Extensions.Logging.LoggerExtensions.Log(ILogger logger, LogLevel logLevel, EventId eventId, Exception exception, String message, Object[] args)\r\n   at Microsoft.Extensions.Logging.LoggerExtensions.Log(ILogger logger, LogLevel logLevel, String message, Object[] args)\r\n   at VistaExamenPlanner.Handler.DatabaseHandler.Select(MySqlCommand sqlCommand) in C:\\Users\\milan\\exameplanner_smort\\exame-tool-api\\Smort-Examen-Tool-API\\VistaExamenPlanner.Handler\\DatabaseHandler.cs:line 70\r\n   at VistaExamenPlanner.Controllers.ExamenPlanner.GetExamensStudent() in C:\\Users\\milan\\exameplanner_smort\\exame-tool-api\\Smort-Examen-Tool-API\\VistaExamenPlanner\\Controllers\\ExamenPlanner.cs:line 40\r\n   at lambda_method2(Closure , Object , Object[] )\r\n   at Microsoft.AspNetCore.Mvc.Infrastructure.ActionMethodExecutor.SyncObjectResultExecutor.Execute(IActionResultTypeMapper mapper, ObjectMethodExecutor executor, Object controller, Object[] arguments)\r\n   at Microsoft.AspNetCore.Mvc.Infrastructure.ControllerActionInvoker.InvokeActionMethodAsync()\r\n   at Microsoft.AspNetCore.Mvc.Infrastructure.ControllerActionInvoker.Next(State& next, Scope& scope, Object& state, Boolean& isCompleted)\r\n   at Microsoft.AspNetCore.Mvc.Infrastructure.ControllerActionInvoker.InvokeNextActionFilterAsync()\r\n--- End of stack trace from previous location ---\r\n   at Microsoft.AspNetCore.Mvc.Infrastructure.ControllerActionInvoker.Rethrow(ActionExecutedContextSealed context)\r\n   at Microsoft.AspNetCore.Mvc.Infrastructure.ControllerActionInvoker.Next(State& next, Scope& scope, Object& state, Boolean& isCompleted)\r\n   at Microsoft.AspNetCore.Mvc.Infrastructure.ControllerActionInvoker.InvokeInnerFilterAsync()\r\n--- End of stack trace from previous location ---\r\n   at Microsoft.AspNetCore.Mvc.Infrastructure.ResourceInvoker.<InvokeNextResourceFilter>g__Awaited|25_0(ResourceInvoker invoker, Task lastTask, State next, Scope scope, Object state, Boolean isCompleted)\r\n   at Microsoft.AspNetCore.Mvc.Infrastructure.ResourceInvoker.Rethrow(ResourceExecutedContextSealed context)\r\n   at Microsoft.AspNetCore.Mvc.Infrastructure.ResourceInvoker.Next(State& next, Scope& scope, Object& state, Boolean& isCompleted)\r\n   at Microsoft.AspNetCore.Mvc.Infrastructure.ResourceInvoker.InvokeFilterPipelineAsync()\r\n--- End of stack trace from previous location ---\r\n   at Microsoft.AspNetCore.Mvc.Infrastructure.ResourceInvoker.<InvokeAsync>g__Awaited|17_0(ResourceInvoker invoker, Task task, IDisposable scope)\r\n   at Microsoft.AspNetCore.Mvc.Infrastructure.ResourceInvoker.<InvokeAsync>g__Awaited|17_0(ResourceInvoker invoker, Task task, IDisposable scope)\r\n   at Microsoft.AspNetCore.Routing.EndpointMiddleware.<Invoke>g__AwaitRequestTask|6_0(Endpoint endpoint, Task requestTask, ILogger logger)\r\n   at Swashbuckle.AspNetCore.SwaggerUI.SwaggerUIMiddleware.Invoke(HttpContext httpContext)\r\n   at Swashbuckle.AspNetCore.Swagger.SwaggerMiddleware.Invoke(HttpContext httpContext, ISwaggerProvider swaggerProvider)\r\n   at Microsoft.AspNetCore.Authentication.AuthenticationMiddleware.Invoke(HttpContext context)\r\n   at Serilog.AspNetCore.RequestLoggingMiddleware.Invoke(HttpContext httpContext)\r\n   at Microsoft.AspNetCore.Watch.BrowserRefresh.BrowserRefreshMiddleware.InvokeAsync(HttpContext context)\r\n   at Microsoft.AspNetCore.Server.Kestrel.Core.Internal.Http.HttpProtocol.ProcessRequests[TContext](IHttpApplication`1 application)","ConnectionId":"0HMTTO305DM0R","TraceIdentifier":"0HMTTO305DM0R:00000001","EventId":{"Id":13,"Name":"ApplicationError"},"SourceContext":"Microsoft.AspNetCore.Server.Kestrel","RequestId":"0HMTTO305DM0R:00000001","RequestPath":"/GetExamenListOfClass","Application":"webApi"}
{"@t":"2023-09-25T12:16:17.0654303Z","@mt":"Database Migrated","Application":"webApi"}
{"@t":"2023-09-25T12:16:17.6449592Z","@mt":"Now listening on: {address}","address":"https://localhost:7167","EventId":{"Id":14,"Name":"ListeningOnAddress"},"SourceContext":"Microsoft.Hosting.Lifetime","Application":"webApi"}
{"@t":"2023-09-25T12:16:17.6507418Z","@mt":"Now listening on: {address}","address":"http://localhost:5263","EventId":{"Id":14,"Name":"ListeningOnAddress"},"SourceContext":"Microsoft.Hosting.Lifetime","Application":"webApi"}
{"@t":"2023-09-25T12:16:17.6554001Z","@mt":"Application started. Press Ctrl+C to shut down.","SourceContext":"Microsoft.Hosting.Lifetime","Application":"webApi"}
{"@t":"2023-09-25T12:16:17.6581467Z","@mt":"Hosting environment: {envName}","envName":"Development","SourceContext":"Microsoft.Hosting.Lifetime","Application":"webApi"}
{"@t":"2023-09-25T12:16:17.6600582Z","@mt":"Content root path: {contentRoot}","contentRoot":"C:\\Users\\milan\\exameplanner_smort\\exame-tool-api\\Smort-Examen-Tool-API\\VistaExamenPlanner","SourceContext":"Microsoft.Hosting.Lifetime","Application":"webApi"}
{"@t":"2023-09-25T12:16:18.9848239Z","@mt":"HTTP {RequestMethod} {RequestPath} responded {StatusCode} in {Elapsed:0.0000} ms","@r":["74.0021"],"RequestMethod":"GET","RequestPath":"/swagger","StatusCode":301,"Elapsed":74.0021,"SourceContext":"Serilog.AspNetCore.RequestLoggingMiddleware","Application":"webApi"}
{"@t":"2023-09-25T12:16:19.3144393Z","@mt":"HTTP {RequestMethod} {RequestPath} responded {StatusCode} in {Elapsed:0.0000} ms","@r":["244.2011"],"RequestMethod":"GET","RequestPath":"/swagger/index.html","StatusCode":200,"Elapsed":244.2011,"SourceContext":"Serilog.AspNetCore.RequestLoggingMiddleware","Application":"webApi"}
{"@t":"2023-09-25T12:16:19.8611094Z","@mt":"HTTP {RequestMethod} {RequestPath} responded {StatusCode} in {Elapsed:0.0000} ms","@r":["93.1214"],"RequestMethod":"GET","RequestPath":"/swagger/v1/swagger.json","StatusCode":200,"Elapsed":93.1214,"SourceContext":"Serilog.AspNetCore.RequestLoggingMiddleware","Application":"webApi"}
{"@t":"2023-09-25T12:17:01.0396408Z","@mt":"HTTP {RequestMethod} {RequestPath} responded {StatusCode} in {Elapsed:0.0000} ms","@r":["25370.4619"],"@l":"Error","@x":"System.ArgumentNullException: Value cannot be null. (Parameter 'logger')\r\n   at System.ThrowHelper.Throw(String paramName)\r\n   at System.ThrowHelper.ThrowIfNull(Object argument, String paramName)\r\n   at Microsoft.Extensions.Logging.LoggerExtensions.Log(ILogger logger, LogLevel logLevel, EventId eventId, Exception exception, String message, Object[] args)\r\n   at Microsoft.Extensions.Logging.LoggerExtensions.Log(ILogger logger, LogLevel logLevel, String message, Object[] args)\r\n   at VistaExamenPlanner.Handler.DatabaseHandler.Select(MySqlCommand sqlCommand) in C:\\Users\\milan\\exameplanner_smort\\exame-tool-api\\Smort-Examen-Tool-API\\VistaExamenPlanner.Handler\\DatabaseHandler.cs:line 70\r\n   at VistaExamenPlanner.Controllers.ExamenPlanner.GetExamensStudent(String klasId) in C:\\Users\\milan\\exameplanner_smort\\exame-tool-api\\Smort-Examen-Tool-API\\VistaExamenPlanner\\Controllers\\ExamenPlanner.cs:line 39\r\n   at lambda_method2(Closure , Object , Object[] )\r\n   at Microsoft.AspNetCore.Mvc.Infrastructure.ActionMethodExecutor.SyncObjectResultExecutor.Execute(IActionResultTypeMapper mapper, ObjectMethodExecutor executor, Object controller, Object[] arguments)\r\n   at Microsoft.AspNetCore.Mvc.Infrastructure.ControllerActionInvoker.InvokeActionMethodAsync()\r\n   at Microsoft.AspNetCore.Mvc.Infrastructure.ControllerActionInvoker.Next(State& next, Scope& scope, Object& state, Boolean& isCompleted)\r\n   at Microsoft.AspNetCore.Mvc.Infrastructure.ControllerActionInvoker.InvokeNextActionFilterAsync()\r\n--- End of stack trace from previous location ---\r\n   at Microsoft.AspNetCore.Mvc.Infrastructure.ControllerActionInvoker.Rethrow(ActionExecutedContextSealed context)\r\n   at Microsoft.AspNetCore.Mvc.Infrastructure.ControllerActionInvoker.Next(State& next, Scope& scope, Object& state, Boolean& isCompleted)\r\n   at Microsoft.AspNetCore.Mvc.Infrastructure.ControllerActionInvoker.InvokeInnerFilterAsync()\r\n--- End of stack trace from previous location ---\r\n   at Microsoft.AspNetCore.Mvc.Infrastructure.ResourceInvoker.<InvokeNextResourceFilter>g__Awaited|25_0(ResourceInvoker invoker, Task lastTask, State next, Scope scope, Object state, Boolean isCompleted)\r\n   at Microsoft.AspNetCore.Mvc.Infrastructure.ResourceInvoker.Rethrow(ResourceExecutedContextSealed context)\r\n   at Microsoft.AspNetCore.Mvc.Infrastructure.ResourceInvoker.Next(State& next, Scope& scope, Object& state, Boolean& isCompleted)\r\n   at Microsoft.AspNetCore.Mvc.Infrastructure.ResourceInvoker.InvokeFilterPipelineAsync()\r\n--- End of stack trace from previous location ---\r\n   at Microsoft.AspNetCore.Mvc.Infrastructure.ResourceInvoker.<InvokeAsync>g__Awaited|17_0(ResourceInvoker invoker, Task task, IDisposable scope)\r\n   at Microsoft.AspNetCore.Mvc.Infrastructure.ResourceInvoker.<InvokeAsync>g__Awaited|17_0(ResourceInvoker invoker, Task task, IDisposable scope)\r\n   at Microsoft.AspNetCore.Routing.EndpointMiddleware.<Invoke>g__AwaitRequestTask|6_0(Endpoint endpoint, Task requestTask, ILogger logger)\r\n   at Swashbuckle.AspNetCore.SwaggerUI.SwaggerUIMiddleware.Invoke(HttpContext httpContext)\r\n   at Swashbuckle.AspNetCore.Swagger.SwaggerMiddleware.Invoke(HttpContext httpContext, ISwaggerProvider swaggerProvider)\r\n   at Microsoft.AspNetCore.Authentication.AuthenticationMiddleware.Invoke(HttpContext context)\r\n   at Serilog.AspNetCore.RequestLoggingMiddleware.Invoke(HttpContext httpContext)","RequestMethod":"GET","RequestPath":"/GetExamenListOfClass","StatusCode":500,"Elapsed":25370.4619,"SourceContext":"Serilog.AspNetCore.RequestLoggingMiddleware","Application":"webApi"}
{"@t":"2023-09-25T12:17:02.7176457Z","@mt":"HTTP {RequestMethod} {RequestPath} responded {StatusCode} in {Elapsed:0.0000} ms","@r":["1679.7175"],"@l":"Error","@x":"System.ArgumentNullException: Value cannot be null. (Parameter 'logger')\r\n   at System.ThrowHelper.Throw(String paramName)\r\n   at System.ThrowHelper.ThrowIfNull(Object argument, String paramName)\r\n   at Microsoft.Extensions.Logging.LoggerExtensions.Log(ILogger logger, LogLevel logLevel, EventId eventId, Exception exception, String message, Object[] args)\r\n   at Microsoft.Extensions.Logging.LoggerExtensions.Log(ILogger logger, LogLevel logLevel, String message, Object[] args)\r\n   at VistaExamenPlanner.Handler.DatabaseHandler.Select(MySqlCommand sqlCommand) in C:\\Users\\milan\\exameplanner_smort\\exame-tool-api\\Smort-Examen-Tool-API\\VistaExamenPlanner.Handler\\DatabaseHandler.cs:line 70\r\n   at VistaExamenPlanner.Controllers.ExamenPlanner.GetExamensStudent(String klasId) in C:\\Users\\milan\\exameplanner_smort\\exame-tool-api\\Smort-Examen-Tool-API\\VistaExamenPlanner\\Controllers\\ExamenPlanner.cs:line 39\r\n   at lambda_method2(Closure , Object , Object[] )\r\n   at Microsoft.AspNetCore.Mvc.Infrastructure.ActionMethodExecutor.SyncObjectResultExecutor.Execute(IActionResultTypeMapper mapper, ObjectMethodExecutor executor, Object controller, Object[] arguments)\r\n   at Microsoft.AspNetCore.Mvc.Infrastructure.ControllerActionInvoker.InvokeActionMethodAsync()\r\n   at Microsoft.AspNetCore.Mvc.Infrastructure.ControllerActionInvoker.Next(State& next, Scope& scope, Object& state, Boolean& isCompleted)\r\n   at Microsoft.AspNetCore.Mvc.Infrastructure.ControllerActionInvoker.InvokeNextActionFilterAsync()\r\n--- End of stack trace from previous location ---\r\n   at Microsoft.AspNetCore.Mvc.Infrastructure.ControllerActionInvoker.Rethrow(ActionExecutedContextSealed context)\r\n   at Microsoft.AspNetCore.Mvc.Infrastructure.ControllerActionInvoker.Next(State& next, Scope& scope, Object& state, Boolean& isCompleted)\r\n   at Microsoft.AspNetCore.Mvc.Infrastructure.ControllerActionInvoker.InvokeInnerFilterAsync()\r\n--- End of stack trace from previous location ---\r\n   at Microsoft.AspNetCore.Mvc.Infrastructure.ResourceInvoker.<InvokeNextResourceFilter>g__Awaited|25_0(ResourceInvoker invoker, Task lastTask, State next, Scope scope, Object state, Boolean isCompleted)\r\n   at Microsoft.AspNetCore.Mvc.Infrastructure.ResourceInvoker.Rethrow(ResourceExecutedContextSealed context)\r\n   at Microsoft.AspNetCore.Mvc.Infrastructure.ResourceInvoker.Next(State& next, Scope& scope, Object& state, Boolean& isCompleted)\r\n   at Microsoft.AspNetCore.Mvc.Infrastructure.ResourceInvoker.InvokeFilterPipelineAsync()\r\n--- End of stack trace from previous location ---\r\n   at Microsoft.AspNetCore.Mvc.Infrastructure.ResourceInvoker.<InvokeAsync>g__Awaited|17_0(ResourceInvoker invoker, Task task, IDisposable scope)\r\n   at Microsoft.AspNetCore.Mvc.Infrastructure.ResourceInvoker.<InvokeAsync>g__Awaited|17_0(ResourceInvoker invoker, Task task, IDisposable scope)\r\n   at Microsoft.AspNetCore.Routing.EndpointMiddleware.<Invoke>g__AwaitRequestTask|6_0(Endpoint endpoint, Task requestTask, ILogger logger)\r\n   at Swashbuckle.AspNetCore.SwaggerUI.SwaggerUIMiddleware.Invoke(HttpContext httpContext)\r\n   at Swashbuckle.AspNetCore.Swagger.SwaggerMiddleware.Invoke(HttpContext httpContext, ISwaggerProvider swaggerProvider)\r\n   at Microsoft.AspNetCore.Authentication.AuthenticationMiddleware.Invoke(HttpContext context)\r\n   at Serilog.AspNetCore.RequestLoggingMiddleware.Invoke(HttpContext httpContext)","RequestMethod":"GET","RequestPath":"/GetExamenListOfClass","StatusCode":500,"Elapsed":1679.7175,"SourceContext":"Serilog.AspNetCore.RequestLoggingMiddleware","Application":"webApi"}
{"@t":"2023-09-25T12:17:02.7069183Z","@mt":"Connection id \"{ConnectionId}\", Request id \"{TraceIdentifier}\": An unhandled exception was thrown by the application.","@l":"Error","@x":"System.ArgumentNullException: Value cannot be null. (Parameter 'logger')\r\n   at System.ThrowHelper.Throw(String paramName)\r\n   at System.ThrowHelper.ThrowIfNull(Object argument, String paramName)\r\n   at Microsoft.Extensions.Logging.LoggerExtensions.Log(ILogger logger, LogLevel logLevel, EventId eventId, Exception exception, String message, Object[] args)\r\n   at Microsoft.Extensions.Logging.LoggerExtensions.Log(ILogger logger, LogLevel logLevel, String message, Object[] args)\r\n   at VistaExamenPlanner.Handler.DatabaseHandler.Select(MySqlCommand sqlCommand) in C:\\Users\\milan\\exameplanner_smort\\exame-tool-api\\Smort-Examen-Tool-API\\VistaExamenPlanner.Handler\\DatabaseHandler.cs:line 70\r\n   at VistaExamenPlanner.Controllers.ExamenPlanner.GetExamensStudent(String klasId) in C:\\Users\\milan\\exameplanner_smort\\exame-tool-api\\Smort-Examen-Tool-API\\VistaExamenPlanner\\Controllers\\ExamenPlanner.cs:line 39\r\n   at lambda_method2(Closure , Object , Object[] )\r\n   at Microsoft.AspNetCore.Mvc.Infrastructure.ActionMethodExecutor.SyncObjectResultExecutor.Execute(IActionResultTypeMapper mapper, ObjectMethodExecutor executor, Object controller, Object[] arguments)\r\n   at Microsoft.AspNetCore.Mvc.Infrastructure.ControllerActionInvoker.InvokeActionMethodAsync()\r\n   at Microsoft.AspNetCore.Mvc.Infrastructure.ControllerActionInvoker.Next(State& next, Scope& scope, Object& state, Boolean& isCompleted)\r\n   at Microsoft.AspNetCore.Mvc.Infrastructure.ControllerActionInvoker.InvokeNextActionFilterAsync()\r\n--- End of stack trace from previous location ---\r\n   at Microsoft.AspNetCore.Mvc.Infrastructure.ControllerActionInvoker.Rethrow(ActionExecutedContextSealed context)\r\n   at Microsoft.AspNetCore.Mvc.Infrastructure.ControllerActionInvoker.Next(State& next, Scope& scope, Object& state, Boolean& isCompleted)\r\n   at Microsoft.AspNetCore.Mvc.Infrastructure.ControllerActionInvoker.InvokeInnerFilterAsync()\r\n--- End of stack trace from previous location ---\r\n   at Microsoft.AspNetCore.Mvc.Infrastructure.ResourceInvoker.<InvokeNextResourceFilter>g__Awaited|25_0(ResourceInvoker invoker, Task lastTask, State next, Scope scope, Object state, Boolean isCompleted)\r\n   at Microsoft.AspNetCore.Mvc.Infrastructure.ResourceInvoker.Rethrow(ResourceExecutedContextSealed context)\r\n   at Microsoft.AspNetCore.Mvc.Infrastructure.ResourceInvoker.Next(State& next, Scope& scope, Object& state, Boolean& isCompleted)\r\n   at Microsoft.AspNetCore.Mvc.Infrastructure.ResourceInvoker.InvokeFilterPipelineAsync()\r\n--- End of stack trace from previous location ---\r\n   at Microsoft.AspNetCore.Mvc.Infrastructure.ResourceInvoker.<InvokeAsync>g__Awaited|17_0(ResourceInvoker invoker, Task task, IDisposable scope)\r\n   at Microsoft.AspNetCore.Mvc.Infrastructure.ResourceInvoker.<InvokeAsync>g__Awaited|17_0(ResourceInvoker invoker, Task task, IDisposable scope)\r\n   at Microsoft.AspNetCore.Routing.EndpointMiddleware.<Invoke>g__AwaitRequestTask|6_0(Endpoint endpoint, Task requestTask, ILogger logger)\r\n   at Swashbuckle.AspNetCore.SwaggerUI.SwaggerUIMiddleware.Invoke(HttpContext httpContext)\r\n   at Swashbuckle.AspNetCore.Swagger.SwaggerMiddleware.Invoke(HttpContext httpContext, ISwaggerProvider swaggerProvider)\r\n   at Microsoft.AspNetCore.Authentication.AuthenticationMiddleware.Invoke(HttpContext context)\r\n   at Serilog.AspNetCore.RequestLoggingMiddleware.Invoke(HttpContext httpContext)\r\n   at Microsoft.AspNetCore.Watch.BrowserRefresh.BrowserRefreshMiddleware.InvokeAsync(HttpContext context)\r\n   at Microsoft.AspNetCore.Server.Kestrel.Core.Internal.Http.HttpProtocol.ProcessRequests[TContext](IHttpApplication`1 application)","ConnectionId":"0HMTTO4S8O2G1","TraceIdentifier":"0HMTTO4S8O2G1:00000009","EventId":{"Id":13,"Name":"ApplicationError"},"SourceContext":"Microsoft.AspNetCore.Server.Kestrel","RequestId":"0HMTTO4S8O2G1:00000009","RequestPath":"/GetExamenListOfClass","Application":"webApi"}
{"@t":"2023-09-25T12:17:02.7718309Z","@mt":"Connection id \"{ConnectionId}\", Request id \"{TraceIdentifier}\": An unhandled exception was thrown by the application.","@l":"Error","@x":"System.ArgumentNullException: Value cannot be null. (Parameter 'logger')\r\n   at System.ThrowHelper.Throw(String paramName)\r\n   at System.ThrowHelper.ThrowIfNull(Object argument, String paramName)\r\n   at Microsoft.Extensions.Logging.LoggerExtensions.Log(ILogger logger, LogLevel logLevel, EventId eventId, Exception exception, String message, Object[] args)\r\n   at Microsoft.Extensions.Logging.LoggerExtensions.Log(ILogger logger, LogLevel logLevel, String message, Object[] args)\r\n   at VistaExamenPlanner.Handler.DatabaseHandler.Select(MySqlCommand sqlCommand) in C:\\Users\\milan\\exameplanner_smort\\exame-tool-api\\Smort-Examen-Tool-API\\VistaExamenPlanner.Handler\\DatabaseHandler.cs:line 70\r\n   at VistaExamenPlanner.Controllers.ExamenPlanner.GetExamensStudent(String klasId) in C:\\Users\\milan\\exameplanner_smort\\exame-tool-api\\Smort-Examen-Tool-API\\VistaExamenPlanner\\Controllers\\ExamenPlanner.cs:line 39\r\n   at lambda_method2(Closure , Object , Object[] )\r\n   at Microsoft.AspNetCore.Mvc.Infrastructure.ActionMethodExecutor.SyncObjectResultExecutor.Execute(IActionResultTypeMapper mapper, ObjectMethodExecutor executor, Object controller, Object[] arguments)\r\n   at Microsoft.AspNetCore.Mvc.Infrastructure.ControllerActionInvoker.InvokeActionMethodAsync()\r\n   at Microsoft.AspNetCore.Mvc.Infrastructure.ControllerActionInvoker.Next(State& next, Scope& scope, Object& state, Boolean& isCompleted)\r\n   at Microsoft.AspNetCore.Mvc.Infrastructure.ControllerActionInvoker.InvokeNextActionFilterAsync()\r\n--- End of stack trace from previous location ---\r\n   at Microsoft.AspNetCore.Mvc.Infrastructure.ControllerActionInvoker.Rethrow(ActionExecutedContextSealed context)\r\n   at Microsoft.AspNetCore.Mvc.Infrastructure.ControllerActionInvoker.Next(State& next, Scope& scope, Object& state, Boolean& isCompleted)\r\n   at Microsoft.AspNetCore.Mvc.Infrastructure.ControllerActionInvoker.InvokeInnerFilterAsync()\r\n--- End of stack trace from previous location ---\r\n   at Microsoft.AspNetCore.Mvc.Infrastructure.ResourceInvoker.<InvokeNextResourceFilter>g__Awaited|25_0(ResourceInvoker invoker, Task lastTask, State next, Scope scope, Object state, Boolean isCompleted)\r\n   at Microsoft.AspNetCore.Mvc.Infrastructure.ResourceInvoker.Rethrow(ResourceExecutedContextSealed context)\r\n   at Microsoft.AspNetCore.Mvc.Infrastructure.ResourceInvoker.Next(State& next, Scope& scope, Object& state, Boolean& isCompleted)\r\n   at Microsoft.AspNetCore.Mvc.Infrastructure.ResourceInvoker.InvokeFilterPipelineAsync()\r\n--- End of stack trace from previous location ---\r\n   at Microsoft.AspNetCore.Mvc.Infrastructure.ResourceInvoker.<InvokeAsync>g__Awaited|17_0(ResourceInvoker invoker, Task task, IDisposable scope)\r\n   at Microsoft.AspNetCore.Mvc.Infrastructure.ResourceInvoker.<InvokeAsync>g__Awaited|17_0(ResourceInvoker invoker, Task task, IDisposable scope)\r\n   at Microsoft.AspNetCore.Routing.EndpointMiddleware.<Invoke>g__AwaitRequestTask|6_0(Endpoint endpoint, Task requestTask, ILogger logger)\r\n   at Swashbuckle.AspNetCore.SwaggerUI.SwaggerUIMiddleware.Invoke(HttpContext httpContext)\r\n   at Swashbuckle.AspNetCore.Swagger.SwaggerMiddleware.Invoke(HttpContext httpContext, ISwaggerProvider swaggerProvider)\r\n   at Microsoft.AspNetCore.Authentication.AuthenticationMiddleware.Invoke(HttpContext context)\r\n   at Serilog.AspNetCore.RequestLoggingMiddleware.Invoke(HttpContext httpContext)\r\n   at Microsoft.AspNetCore.Watch.BrowserRefresh.BrowserRefreshMiddleware.InvokeAsync(HttpContext context)\r\n   at Microsoft.AspNetCore.Server.Kestrel.Core.Internal.Http.HttpProtocol.ProcessRequests[TContext](IHttpApplication`1 application)","ConnectionId":"0HMTTO4S8O2G3","TraceIdentifier":"0HMTTO4S8O2G3:00000001","EventId":{"Id":13,"Name":"ApplicationError"},"SourceContext":"Microsoft.AspNetCore.Server.Kestrel","RequestId":"0HMTTO4S8O2G3:00000001","RequestPath":"/GetExamenListOfClass","Application":"webApi"}
{"@t":"2023-09-25T12:17:02.8633233Z","@mt":"HTTP {RequestMethod} {RequestPath} responded {StatusCode} in {Elapsed:0.0000} ms","@r":["1825.2109"],"RequestMethod":"GET","RequestPath":"/GetExamensList","StatusCode":200,"Elapsed":1825.2109,"SourceContext":"Serilog.AspNetCore.RequestLoggingMiddleware","Application":"webApi"}
{"@t":"2023-09-25T12:17:02.8633193Z","@mt":"HTTP {RequestMethod} {RequestPath} responded {StatusCode} in {Elapsed:0.0000} ms","@r":["1852.4949"],"RequestMethod":"GET","RequestPath":"/GetExamensList","StatusCode":200,"Elapsed":1852.4949,"SourceContext":"Serilog.AspNetCore.RequestLoggingMiddleware","Application":"webApi"}
{"@t":"2023-09-25T12:17:12.3013038Z","@mt":"HTTP {RequestMethod} {RequestPath} responded {StatusCode} in {Elapsed:0.0000} ms","@r":["7.5612"],"RequestMethod":"GET","RequestPath":"/GetExamensList","StatusCode":200,"Elapsed":7.5612,"SourceContext":"Serilog.AspNetCore.RequestLoggingMiddleware","Application":"webApi"}
